{
  "schemaVersion": 1,
  "id": "functional-starscript",
  "version": "${version}",
  "name": "Functional Starscript",
  "description": "You wont need most of this.",
  "authors": [
    "Crosby"
  ],
  "contact": {
    "repo": "https://github.com/RacoonDog/FunctionalStarscript",
    "sources": "https://github.com/RacoonDog/FunctionalStarscript",
    "issues": "https://github.com/RacoonDog/FunctionalStarscript/issues"
  },
  "license": "MPL-2.0",
  "icon": "assets/functional-starscript/icon.png",
  "environment": "client",
  "entrypoints": {
    "meteor": [
      "io.github.racoondog.functionalstarscript.FunctionalStarscript"
    ]
  },
  "mixins": [
    "functional-starscript.mixins.json"
  ],
  "custom": {
    "meteor-client:color": "225,25,25",
    "modmenu": {
      "badges": [ "meteor" ]
    }
  },
  "depends": {
    "java": ">=17",
    "fabricloader": ">=0.12",
    "minecraft": ">=${mc_version}",
    "meteor-client": "*"
  }
}
